LICENSE.txt
MANIFEST.in
README
setup.py
juegodeguerrajavier.egg-info/PKG-INFO
juegodeguerrajavier.egg-info/SOURCES.txt
juegodeguerrajavier.egg-info/dependency_links.txt
juegodeguerrajavier.egg-info/top_level.txt
wargame/__init__.py
wargame/abstractgameunit.py
wargame/attackoftheorcs.py
wargame/gameuniterror.py
wargame/gameutils.py
wargame/hut.py
wargame/knight.py
wargame/orcrider.py