Metadata-Version: 1.0
Name: juegodeguerrajavier
Version: 7.1.2
Summary: fantasiaAtaqueaOrcos1113
Home-page: https://tespypi.python.org/pypi/ataqueaOrcos1112/
Author: jmartinacero
Author-email: javiermartin@jmrobotica.com
License: LICENSE.txt
Platform: UNKNOWN
